pacifica_proxy-0.1.6-py3.8-nspkg.pth
pacifica/proxy/__init__.py
pacifica/proxy/__main__.py
pacifica/proxy/config.py
pacifica/proxy/files.py
pacifica/proxy/globals.py
pacifica/proxy/rest.py
pacifica/proxy/wsgi.py
pacifica_proxy-0.1.6.dist-info/LICENSE
pacifica_proxy-0.1.6.dist-info/METADATA
pacifica_proxy-0.1.6.dist-info/WHEEL
pacifica_proxy-0.1.6.dist-info/entry_points.txt
pacifica_proxy-0.1.6.dist-info/namespace_packages.txt
pacifica_proxy-0.1.6.dist-info/top_level.txt
pacifica_proxy-0.1.6.dist-info/RECORD
