Metadata-Version: 2.1
Name: pacifica-proxy
Version: 0.1.6
Summary: Pacifica Proxy
Home-page: https://github.com/pacifica/pacifica-uniqueid/
Author: David Brown
Author-email: david.brown@pnnl.gov
License: UNKNOWN
Platform: UNKNOWN
Requires-Dist: cherrypy
Requires-Dist: pacifica-namespace
Requires-Dist: requests
